{
  "id": 1302110,
  "fleet_prefab": [],
  "map_id": 10001,
  "stages": [
    {
      "timeCount": 180,
      "failCondition": 1,
      "playerArea": [
        -70,
        20,
        37,
        68
      ],
      "stageIndex": 1,
      "backGroundStageID": 1,
      "totalArea": [
        -70,
        20,
        90,
        70
      ],
      "fleetCorrdinate": [
        -80,
        0,
        75
      ],
      "mainUnitPosition": {
        "1": [
          [
            -105,
            0,
            58
          ],
          [
            -105,
            0,
            78
          ],
          [
            -105,
            0,
            38
          ]
        ],
        "-1": [
          [
            15,
            0,
            58
          ],
          [
            15,
            0,
            78
          ],
          [
            15,
            0,
            38
          ]
        ]
      },
      "enemyArea": [],
      "passCondition": 1,
      "waves": [
        {
          "preWaves": [],
          "waveIndex": 1001,
          "triggerType": 1,
          "triggerParams": {
            "timeout": 1
          }
        },
        {
          "preWaves": [],
          "waveIndex": 1002,
          "triggerType": 1,
          "triggerParams": {
            "timeout": 15
          }
        },
        {
          "preWaves": [],
          "waveIndex": 1003,
          "triggerType": 1,
          "triggerParams": {
            "timeout": 30
          }
        },
        {
          "preWaves": [
            1001
          ],
          "triggerType": 0,
          "conditionType": 1,
          "spawn": [
            {
              "moveCast": true,
              "corrdinate": [
                5,
                0,
                85
              ],
              "buffList": [
                8001
              ],
              "monsterTemplateID": 13037,
              "delay": 0,
              "phase": [
                {
                  "setAI": 20007,
                  "switchTo": 1,
                  "dive": "STATE_RAID",
                  "switchParam": 10,
                  "switchType": 1,
                  "index": 0
                },
                {
                  "setAI": 20009,
                  "index": 1,
                  "dive": "STATE_RAID",
                  "switchParam": 10,
                  "switchType": 1
                }
              ]
            }
          ],
          "waveIndex": 2001,
          "key": true,
          "triggerParam": []
        },
        {
          "preWaves": [
            1002,
            2001
          ],
          "triggerType": 0,
          "conditionType": 1,
          "spawn": [
            {
              "moveCast": true,
              "corrdinate": [
                5,
                0,
                30
              ],
              "buffList": [
                8001
              ],
              "monsterTemplateID": 13037,
              "delay": 0,
              "phase": [
                {
                  "setAI": 20008,
                  "switchTo": 1,
                  "dive": "STATE_RAID",
                  "switchParam": 10,
                  "switchType": 1,
                  "index": 0
                },
                {
                  "setAI": 20009,
                  "index": 1,
                  "dive": "STATE_DIVE",
                  "switchParam": 10,
                  "switchType": 1
                }
              ]
            }
          ],
          "waveIndex": 2002,
          "key": true,
          "triggerParam": []
        },
        {
          "reinforcement": [
            {
              "moveCast": true,
              "corrdinate": [
                30,
                0,
                40
              ],
              "buffList": [
                8001,
                8002
              ],
              "monsterTemplateID": 13039,
              "delay": 0
            },
            {
              "moveCast": true,
              "corrdinate": [
                30,
                0,
                70
              ],
              "buffList": [
                8001,
                8002
              ],
              "monsterTemplateID": 13039,
              "delay": 0
            }
          ],
          "preWaves": [
            1003,
            2002
          ],
          "triggerType": 0,
          "conditionType": 1,
          "spawn": [
            {
              "moveCast": true,
              "corrdinate": [
                5,
                0,
                85
              ],
              "buffList": [
                8001
              ],
              "monsterTemplateID": 13037,
              "delay": 0,
              "phase": [
                {
                  "setAI": 20007,
                  "switchTo": 1,
                  "dive": "STATE_RAID",
                  "switchParam": 10,
                  "switchType": 1,
                  "index": 0
                },
                {
                  "setAI": 20009,
                  "index": 1,
                  "dive": "STATE_RAID",
                  "switchParam": 10,
                  "switchType": 1
                }
              ]
            },
            {
              "moveCast": true,
              "corrdinate": [
                5,
                0,
                30
              ],
              "buffList": [
                8001
              ],
              "monsterTemplateID": 13037,
              "delay": 0,
              "phase": [
                {
                  "setAI": 20008,
                  "switchTo": 1,
                  "dive": "STATE_RAID",
                  "switchParam": 10,
                  "switchType": 1,
                  "index": 0
                },
                {
                  "setAI": 20009,
                  "index": 1,
                  "dive": "STATE_RAID",
                  "switchParam": 10,
                  "switchType": 1
                }
              ]
            }
          ],
          "waveIndex": 2003,
          "key": true,
          "triggerParam": []
        },
        {
          "preWaves": [],
          "waveIndex": 100,
          "triggerType": 1,
          "triggerParams": {
            "timeout": 0.5
          }
        },
        {
          "preWaves": [],
          "waveIndex": 202,
          "triggerType": 1,
          "triggerParams": {
            "timeout": 15
          }
        },
        {
          "preWaves": [],
          "waveIndex": 203,
          "triggerType": 1,
          "triggerParams": {
            "timeout": 30
          }
        },
        {
          "airFighter": [
            {
              "totalNumber": 6,
              "templateID": 340010,
              "attr": {
                "attackRating": 23,
                "maxHP": 999,
                "airPower": 40
              },
              "formation": 10006,
              "interval": 1,
              "onceNumber": 6,
              "delay": 0,
              "weaponID": [
                340008
              ]
            }
          ],
          "preWaves": [
            100
          ],
          "triggerType": 0,
          "conditionType": 1,
          "spawn": [
            {
              "moveCast": true,
              "corrdinate": [
                0,
                0,
                80
              ],
              "buffList": [
                8001,
                8007
              ],
              "monsterTemplateID": 13001,
              "delay": 0
            },
            {
              "moveCast": true,
              "monsterTemplateID": 13013,
              "delay": 0,
              "corrdinate": [
                -15,
                0,
                55
              ]
            },
            {
              "moveCast": true,
              "corrdinate": [
                10,
                0,
                55
              ],
              "buffList": [
                8001,
                8007
              ],
              "monsterTemplateID": 13002,
              "delay": 0
            },
            {
              "moveCast": true,
              "corrdinate": [
                0,
                0,
                30
              ],
              "buffList": [
                8001,
                8007
              ],
              "monsterTemplateID": 13001,
              "delay": 0
            }
          ],
          "waveIndex": 101,
          "key": true,
          "triggerParam": []
        },
        {
          "airFighter": [
            {
              "totalNumber": 6,
              "templateID": 340010,
              "attr": {
                "attackRating": 23,
                "maxHP": 999,
                "airPower": 40
              },
              "formation": 10006,
              "interval": 1,
              "onceNumber": 6,
              "delay": 0,
              "weaponID": [
                340008
              ]
            }
          ],
          "reinforcement": [
            {
              "moveCast": true,
              "corrdinate": [
                10,
                0,
                70
              ],
              "buffList": [
                8001,
                8007
              ],
              "monsterTemplateID": 13002,
              "delay": 0
            },
            {
              "moveCast": true,
              "corrdinate": [
                0,
                0,
                55
              ],
              "buffList": [
                8001,
                8007
              ],
              "monsterTemplateID": 13005,
              "delay": 0
            },
            {
              "moveCast": true,
              "corrdinate": [
                10,
                0,
                40
              ],
              "buffList": [
                8001,
                8007
              ],
              "monsterTemplateID": 13002,
              "delay": 0
            }
          ],
          "triggerType": 0,
          "waveIndex": 102,
          "triggerParam": [],
          "preWaves": [
            101,
            202
          ],
          "key": true,
          "conditionType": 1,
          "spawn": [
            {
              "reinforceDelay": 6,
              "corrdinate": [
                -15,
                0,
                55
              ],
              "monsterTemplateID": 13020,
              "delay": 0,
              "moveCast": true
            }
          ]
        },
        {
          "reinforcement": [
            {
              "moveCast": true,
              "corrdinate": [
                10,
                0,
                75
              ],
              "buffList": [
                8001,
                8007
              ],
              "monsterTemplateID": 13002,
              "delay": 0
            },
            {
              "moveCast": true,
              "corrdinate": [
                0,
                0,
                65
              ],
              "buffList": [
                8001,
                8007
              ],
              "monsterTemplateID": 13004,
              "delay": 0
            },
            {
              "moveCast": true,
              "corrdinate": [
                0,
                0,
                45
              ],
              "buffList": [
                8001,
                8007
              ],
              "monsterTemplateID": 13004,
              "delay": 0
            },
            {
              "moveCast": true,
              "corrdinate": [
                10,
                0,
                35
              ],
              "buffList": [
                8001,
                8007
              ],
              "monsterTemplateID": 13002,
              "delay": 0
            }
          ],
          "preWaves": [
            102,
            101
          ],
          "triggerType": 0,
          "conditionType": 0,
          "spawn": [
            {
              "reinforceDelay": 6,
              "corrdinate": [
                -15,
                0,
                70
              ],
              "buffList": [
                8050,
                8051
              ],
              "monsterTemplateID": 13022,
              "delay": 0,
              "moveCast": true
            },
            {
              "reinforceDelay": 6,
              "corrdinate": [
                -15,
                0,
                40
              ],
              "buffList": [
                8050,
                8051
              ],
              "monsterTemplateID": 13011,
              "delay": 0,
              "moveCast": true
            }
          ],
          "waveIndex": 103,
          "key": true,
          "triggerParam": []
        },
        {
          "preWaves": [
            103,
            2003
          ],
          "triggerType": 8,
          "conditionType": 0,
          "waveIndex": 900,
          "triggerParams": []
        }
      ]
    }
  ]
}