{
  "950132": {
    "search_type": 1,
    "attack_attribute": 1,
    "shakescreen": 0,
    "angle": 180,
    "reload_max": 600,
    "torpedo_ammo": 0,
    "queue": 3,
    "name": "【挑战关卡7】提尔比茨_爆炸圈",
    "fire_fx": "CAFire",
    "charge_param": "",
    "suppress": 1,
    "range": 90,
    "recover_time": 0,
    "fire_fx_loop_type": 1,
    "precast_param": [],
    "expose": 0,
    "attack_attribute_ratio": 100,
    "damage": 13,
    "action_index": "attack",
    "type": 1,
    "search_condition": [
      1
    ],
    "oxy_type": [
      1
    ],
    "id": 950132,
    "spawn_bound": "cannon",
    "barrage_ID": [
      950103,
      950104
    ],
    "corrected": 100,
    "auto_aftercast": 0,
    "bullet_ID": [
      470341,
      470342
    ],
    "min_range": 0,
    "initial_over_heat": 0,
    "aim_type": 0,
    "fire_sfx": "battle/cannon-main",
    "effect_move": 0,
    "axis_angle": 0
  },
  "950138": {
    "search_type": 1,
    "attack_attribute": 1,
    "shakescreen": 0,
    "angle": 180,
    "reload_max": 800,
    "torpedo_ammo": 0,
    "queue": 4,
    "name": "【挑战关卡7】提尔比茨_爆炸圈旋转",
    "fire_fx": "CAFire",
    "charge_param": "",
    "suppress": 1,
    "range": 90,
    "recover_time": 0,
    "fire_fx_loop_type": 1,
    "precast_param": [],
    "expose": 0,
    "attack_attribute_ratio": 100,
    "damage": 13,
    "action_index": "attack",
    "type": 1,
    "search_condition": [
      1
    ],
    "oxy_type": [
      1
    ],
    "id": 950138,
    "spawn_bound": "cannon",
    "barrage_ID": [
      950115,
      950116
    ],
    "corrected": 100,
    "auto_aftercast": 0,
    "bullet_ID": [
      470385,
      470386
    ],
    "min_range": 0,
    "initial_over_heat": 0,
    "aim_type": 0,
    "fire_sfx": "battle/cannon-main",
    "effect_move": 0,
    "axis_angle": 0
  },
  "900111": {
    "search_type": 1,
    "attack_attribute": 1,
    "shakescreen": 0,
    "angle": 360,
    "reload_max": 500,
    "torpedo_ammo": 0,
    "queue": 4,
    "name": "【挑战关卡4】跨射炮",
    "fire_fx": "CLFire",
    "charge_param": "",
    "suppress": 1,
    "range": 90,
    "recover_time": 0,
    "fire_fx_loop_type": 3,
    "precast_param": [],
    "expose": 0,
    "attack_attribute_ratio": 100,
    "damage": 19,
    "action_index": "attack",
    "type": 1,
    "search_condition": [
      1
    ],
    "oxy_type": [
      1
    ],
    "id": 900111,
    "spawn_bound": "cannon",
    "barrage_ID": [
      900111
    ],
    "corrected": 105,
    "auto_aftercast": 0,
    "bullet_ID": [
      900111
    ],
    "min_range": 0,
    "initial_over_heat": 0,
    "aim_type": 1,
    "fire_sfx": "battle/cannon-155mm",
    "effect_move": 0,
    "axis_angle": 0
  },
  "950136": {
    "search_type": 1,
    "attack_attribute": 1,
    "shakescreen": 0,
    "angle": 180,
    "reload_max": 600,
    "torpedo_ammo": 0,
    "queue": 2,
    "name": "【挑战关卡7】提尔比茨_爆炸圈旋转",
    "fire_fx": "CAFire",
    "charge_param": "",
    "suppress": 1,
    "range": 90,
    "recover_time": 0,
    "fire_fx_loop_type": 1,
    "precast_param": [],
    "expose": 0,
    "attack_attribute_ratio": 100,
    "damage": 13,
    "action_index": "attack",
    "type": 1,
    "search_condition": [
      1
    ],
    "oxy_type": [
      1
    ],
    "id": 950136,
    "spawn_bound": "cannon",
    "barrage_ID": [
      950111,
      950112
    ],
    "corrected": 100,
    "auto_aftercast": 0,
    "bullet_ID": [
      470381,
      470382
    ],
    "min_range": 0,
    "initial_over_heat": 0,
    "aim_type": 0,
    "fire_sfx": "battle/cannon-main",
    "effect_move": 0,
    "axis_angle": 0
  },
  "910003": {
    "search_type": 1,
    "attack_attribute": 1,
    "shakescreen": 0,
    "angle": 360,
    "reload_max": 500,
    "torpedo_ammo": 0,
    "queue": 3,
    "name": "【挑战关卡3】散布_旋转_上",
    "fire_fx": "CLFire",
    "charge_param": "",
    "suppress": 1,
    "range": 90,
    "recover_time": 0,
    "fire_fx_loop_type": 3,
    "precast_param": [],
    "expose": 0,
    "attack_attribute_ratio": 100,
    "damage": 19,
    "action_index": "attack",
    "type": 1,
    "search_condition": [
      1
    ],
    "oxy_type": [
      1
    ],
    "id": 910003,
    "spawn_bound": "cannon",
    "barrage_ID": [
      910001,
      910002,
      910003
    ],
    "corrected": 105,
    "auto_aftercast": 0,
    "bullet_ID": [
      910007,
      910008,
      910009
    ],
    "min_range": 0,
    "initial_over_heat": 0,
    "aim_type": 1,
    "fire_sfx": "battle/cannon-155mm",
    "effect_move": 0,
    "axis_angle": 0
  },
  "900081": {
    "search_type": 1,
    "attack_attribute": 1,
    "shakescreen": 0,
    "angle": 360,
    "reload_max": 400,
    "torpedo_ammo": 0,
    "queue": 1,
    "name": "【挑战关卡4】弧形散射",
    "fire_fx": "CLFire",
    "charge_param": "",
    "suppress": 1,
    "range": 90,
    "recover_time": 0,
    "fire_fx_loop_type": 3,
    "precast_param": [],
    "expose": 0,
    "attack_attribute_ratio": 100,
    "damage": 19,
    "action_index": "attack",
    "type": 1,
    "search_condition": [
      1
    ],
    "oxy_type": [
      1
    ],
    "id": 900081,
    "spawn_bound": "cannon",
    "barrage_ID": [
      900081,
      900082
    ],
    "corrected": 105,
    "auto_aftercast": 0,
    "bullet_ID": [
      900081,
      900082
    ],
    "min_range": 0,
    "initial_over_heat": 0,
    "aim_type": 0,
    "fire_sfx": "battle/cannon-155mm",
    "effect_move": 0,
    "axis_angle": 0
  },
  "910004": {
    "search_type": 1,
    "attack_attribute": 1,
    "shakescreen": 0,
    "angle": 360,
    "reload_max": 500,
    "torpedo_ammo": 0,
    "queue": 1,
    "name": "【挑战关卡3】散布_短",
    "fire_fx": "CLFire",
    "charge_param": "",
    "suppress": 1,
    "range": 90,
    "recover_time": 0,
    "fire_fx_loop_type": 3,
    "precast_param": [],
    "expose": 0,
    "attack_attribute_ratio": 100,
    "damage": 19,
    "action_index": "attack",
    "type": 1,
    "search_condition": [
      1
    ],
    "oxy_type": [
      1
    ],
    "id": 910004,
    "spawn_bound": "cannon",
    "barrage_ID": [
      910004,
      910005,
      910006
    ],
    "corrected": 105,
    "auto_aftercast": 0,
    "bullet_ID": [
      910001,
      910002,
      910003
    ],
    "min_range": 0,
    "initial_over_heat": 0,
    "aim_type": 1,
    "fire_sfx": "battle/cannon-155mm",
    "effect_move": 0,
    "axis_angle": 0
  },
  "900082": {
    "search_type": 1,
    "attack_attribute": 1,
    "shakescreen": 0,
    "angle": 360,
    "reload_max": 400,
    "torpedo_ammo": 0,
    "queue": 2,
    "name": "【挑战关卡4】弧形散射_下",
    "fire_fx": "CLFire",
    "charge_param": "",
    "suppress": 1,
    "range": 90,
    "recover_time": 0,
    "fire_fx_loop_type": 3,
    "precast_param": [],
    "expose": 0,
    "attack_attribute_ratio": 100,
    "damage": 19,
    "action_index": "attack",
    "type": 1,
    "search_condition": [
      1
    ],
    "oxy_type": [
      1
    ],
    "id": 900082,
    "spawn_bound": "cannon",
    "barrage_ID": [
      900082
    ],
    "corrected": 105,
    "auto_aftercast": 0,
    "bullet_ID": [
      900082
    ],
    "min_range": 0,
    "initial_over_heat": 0,
    "aim_type": 0,
    "fire_sfx": "battle/cannon-155mm",
    "effect_move": 0,
    "axis_angle": 0
  },
  "910005": {
    "search_type": 1,
    "attack_attribute": 1,
    "shakescreen": 0,
    "angle": 360,
    "reload_max": 500,
    "torpedo_ammo": 0,
    "queue": 1,
    "name": "【挑战关卡3】散布_旋转_上下",
    "fire_fx": "CLFire",
    "charge_param": "",
    "suppress": 1,
    "range": 90,
    "recover_time": 0,
    "fire_fx_loop_type": 3,
    "precast_param": [],
    "expose": 0,
    "attack_attribute_ratio": 100,
    "damage": 19,
    "action_index": "attack",
    "type": 1,
    "search_condition": [
      1
    ],
    "oxy_type": [
      1
    ],
    "id": 910005,
    "spawn_bound": "cannon",
    "barrage_ID": [
      910007,
      910008,
      910009,
      910007,
      910008,
      910009
    ],
    "corrected": 105,
    "auto_aftercast": 0,
    "bullet_ID": [
      910004,
      910005,
      910006,
      910007,
      910008,
      910009
    ],
    "min_range": 0,
    "initial_over_heat": 0,
    "aim_type": 1,
    "fire_sfx": "battle/cannon-155mm",
    "effect_move": 0,
    "axis_angle": 0
  },
  "900083": {
    "search_type": 1,
    "attack_attribute": 1,
    "shakescreen": 0,
    "angle": 360,
    "reload_max": 400,
    "torpedo_ammo": 0,
    "queue": 2,
    "name": "【挑战关卡4】弧线连射_上下轮流",
    "fire_fx": "CLFire",
    "charge_param": "",
    "suppress": 1,
    "range": 90,
    "recover_time": 0,
    "fire_fx_loop_type": 3,
    "precast_param": [],
    "expose": 0,
    "attack_attribute_ratio": 100,
    "damage": 19,
    "action_index": "attack",
    "type": 1,
    "search_condition": [
      1
    ],
    "oxy_type": [
      1
    ],
    "id": 900083,
    "spawn_bound": "cannon",
    "barrage_ID": [
      900083,
      900084
    ],
    "corrected": 105,
    "auto_aftercast": 0,
    "bullet_ID": [
      900085,
      900086
    ],
    "min_range": 0,
    "initial_over_heat": 0,
    "aim_type": 0,
    "fire_sfx": "battle/cannon-155mm",
    "effect_move": 0,
    "axis_angle": 0
  },
  "950137": {
    "search_type": 1,
    "attack_attribute": 1,
    "shakescreen": 0,
    "angle": 180,
    "reload_max": 700,
    "torpedo_ammo": 0,
    "queue": 3,
    "name": "【挑战关卡7】提尔比茨_爆炸圈旋转",
    "fire_fx": "CAFire",
    "charge_param": "",
    "suppress": 1,
    "range": 90,
    "recover_time": 0,
    "fire_fx_loop_type": 1,
    "precast_param": [],
    "expose": 0,
    "attack_attribute_ratio": 100,
    "damage": 13,
    "action_index": "attack",
    "type": 1,
    "search_condition": [
      1
    ],
    "oxy_type": [
      1
    ],
    "id": 950137,
    "spawn_bound": "cannon",
    "barrage_ID": [
      950113,
      950114
    ],
    "corrected": 100,
    "auto_aftercast": 0,
    "bullet_ID": [
      470383,
      470384
    ],
    "min_range": 0,
    "initial_over_heat": 0,
    "aim_type": 0,
    "fire_sfx": "battle/cannon-main",
    "effect_move": 0,
    "axis_angle": 0
  },
  "900084": {
    "search_type": 1,
    "attack_attribute": 1,
    "shakescreen": 0,
    "angle": 360,
    "reload_max": 500,
    "torpedo_ammo": 0,
    "queue": 1,
    "name": "【挑战关卡4】弧形散射_合",
    "fire_fx": "CLFire",
    "charge_param": "",
    "suppress": 1,
    "range": 90,
    "recover_time": 0,
    "fire_fx_loop_type": 3,
    "precast_param": [],
    "expose": 0,
    "attack_attribute_ratio": 100,
    "damage": 19,
    "action_index": "attack",
    "type": 1,
    "search_condition": [
      1
    ],
    "oxy_type": [
      1
    ],
    "id": 900084,
    "spawn_bound": "cannon",
    "barrage_ID": [
      900085,
      900086
    ],
    "corrected": 105,
    "auto_aftercast": 0,
    "bullet_ID": [
      900085,
      900086
    ],
    "min_range": 0,
    "initial_over_heat": 0,
    "aim_type": 0,
    "fire_sfx": "battle/cannon-155mm",
    "effect_move": 0,
    "axis_angle": 0
  },
  "900431": {
    "search_type": 1,
    "attack_attribute": 1,
    "shakescreen": 0,
    "angle": 360,
    "reload_max": 500,
    "torpedo_ammo": 0,
    "queue": 8,
    "name": "【挑战关卡4】波浪",
    "fire_fx": "CLFire",
    "charge_param": "",
    "suppress": 1,
    "range": 90,
    "recover_time": 0,
    "fire_fx_loop_type": 3,
    "precast_param": [],
    "expose": 0,
    "attack_attribute_ratio": 100,
    "damage": 19,
    "action_index": "attack",
    "type": 1,
    "search_condition": [
      1
    ],
    "oxy_type": [
      1
    ],
    "id": 900431,
    "spawn_bound": "cannon",
    "barrage_ID": [
      903401
    ],
    "corrected": 105,
    "auto_aftercast": 0,
    "bullet_ID": [
      900431
    ],
    "min_range": 0,
    "initial_over_heat": 0,
    "aim_type": 1,
    "fire_sfx": "battle/cannon-155mm",
    "effect_move": 0,
    "axis_angle": 0
  },
  "900085": {
    "search_type": 1,
    "attack_attribute": 1,
    "shakescreen": 0,
    "angle": 360,
    "reload_max": 500,
    "torpedo_ammo": 0,
    "queue": 1,
    "name": "【挑战关卡4】弧形散射_合_15度",
    "fire_fx": "CLFire",
    "charge_param": "",
    "suppress": 1,
    "range": 90,
    "recover_time": 0,
    "fire_fx_loop_type": 3,
    "precast_param": [],
    "expose": 0,
    "attack_attribute_ratio": 100,
    "damage": 19,
    "action_index": "attack",
    "type": 1,
    "search_condition": [
      1
    ],
    "oxy_type": [
      1
    ],
    "id": 900085,
    "spawn_bound": "cannon",
    "barrage_ID": [
      900087,
      900088,
      900089,
      900090
    ],
    "corrected": 105,
    "auto_aftercast": 0,
    "bullet_ID": [
      900085,
      900086,
      900085,
      900086
    ],
    "min_range": 0,
    "initial_over_heat": 0,
    "aim_type": 0,
    "fire_sfx": "battle/cannon-155mm",
    "effect_move": 0,
    "axis_angle": 0
  },
  "900432": {
    "search_type": 1,
    "attack_attribute": 1,
    "shakescreen": 0,
    "angle": 360,
    "reload_max": 500,
    "torpedo_ammo": 0,
    "queue": 8,
    "name": "【挑战关卡4】波浪_反",
    "fire_fx": "CLFire",
    "charge_param": "",
    "suppress": 1,
    "range": 90,
    "recover_time": 0,
    "fire_fx_loop_type": 3,
    "precast_param": [],
    "expose": 0,
    "attack_attribute_ratio": 100,
    "damage": 19,
    "action_index": "attack",
    "type": 1,
    "search_condition": [
      1
    ],
    "oxy_type": [
      1
    ],
    "id": 900432,
    "spawn_bound": "cannon",
    "barrage_ID": [
      903411
    ],
    "corrected": 105,
    "auto_aftercast": 0,
    "bullet_ID": [
      900431
    ],
    "min_range": 0,
    "initial_over_heat": 0,
    "aim_type": 0,
    "fire_sfx": "battle/cannon-155mm",
    "effect_move": 0,
    "axis_angle": 0
  },
  "950135": {
    "search_type": 1,
    "attack_attribute": 1,
    "shakescreen": 0,
    "angle": 180,
    "reload_max": 900,
    "torpedo_ammo": 0,
    "queue": 6,
    "name": "【挑战关卡7】提尔比茨_爆炸圈",
    "fire_fx": "CAFire",
    "charge_param": "",
    "suppress": 1,
    "range": 90,
    "recover_time": 0,
    "fire_fx_loop_type": 1,
    "precast_param": [],
    "expose": 0,
    "attack_attribute_ratio": 100,
    "damage": 13,
    "action_index": "attack",
    "type": 1,
    "search_condition": [
      1
    ],
    "oxy_type": [
      1
    ],
    "id": 950135,
    "spawn_bound": "cannon",
    "barrage_ID": [
      950109,
      950110
    ],
    "corrected": 100,
    "auto_aftercast": 0,
    "bullet_ID": [
      470371,
      470372
    ],
    "min_range": 0,
    "initial_over_heat": 0,
    "aim_type": 0,
    "fire_sfx": "battle/cannon-main",
    "effect_move": 0,
    "axis_angle": 0
  },
  "900433": {
    "search_type": 1,
    "attack_attribute": 1,
    "shakescreen": 0,
    "angle": 360,
    "reload_max": 500,
    "torpedo_ammo": 0,
    "queue": 8,
    "name": "【挑战关卡4】波浪_长",
    "fire_fx": "CLFire",
    "charge_param": "",
    "suppress": 1,
    "range": 90,
    "recover_time": 0,
    "fire_fx_loop_type": 3,
    "precast_param": [],
    "expose": 0,
    "attack_attribute_ratio": 100,
    "damage": 19,
    "action_index": "attack",
    "type": 1,
    "search_condition": [
      1
    ],
    "oxy_type": [
      1
    ],
    "id": 900433,
    "spawn_bound": "cannon",
    "barrage_ID": [
      903402
    ],
    "corrected": 105,
    "auto_aftercast": 0,
    "bullet_ID": [
      900431
    ],
    "min_range": 0,
    "initial_over_heat": 0,
    "aim_type": 1,
    "fire_sfx": "battle/cannon-155mm",
    "effect_move": 0,
    "axis_angle": 0
  },
  "950134": {
    "search_type": 1,
    "attack_attribute": 1,
    "shakescreen": 0,
    "angle": 180,
    "reload_max": 800,
    "torpedo_ammo": 0,
    "queue": 5,
    "name": "【挑战关卡7】提尔比茨_爆炸圈",
    "fire_fx": "CAFire",
    "charge_param": "",
    "suppress": 1,
    "range": 90,
    "recover_time": 0,
    "fire_fx_loop_type": 1,
    "precast_param": [],
    "expose": 0,
    "attack_attribute_ratio": 100,
    "damage": 13,
    "action_index": "attack",
    "type": 1,
    "search_condition": [
      1
    ],
    "oxy_type": [
      1
    ],
    "id": 950134,
    "spawn_bound": "cannon",
    "barrage_ID": [
      950107,
      950108
    ],
    "corrected": 100,
    "auto_aftercast": 0,
    "bullet_ID": [
      470361,
      470362
    ],
    "min_range": 0,
    "initial_over_heat": 0,
    "aim_type": 0,
    "fire_sfx": "battle/cannon-main",
    "effect_move": 0,
    "axis_angle": 0
  },
  "900434": {
    "search_type": 1,
    "attack_attribute": 1,
    "shakescreen": 0,
    "angle": 360,
    "reload_max": 500,
    "torpedo_ammo": 0,
    "queue": 8,
    "name": "【挑战关卡4】波浪_反_长",
    "fire_fx": "CLFire",
    "charge_param": "",
    "suppress": 1,
    "range": 90,
    "recover_time": 0,
    "fire_fx_loop_type": 3,
    "precast_param": [],
    "expose": 0,
    "attack_attribute_ratio": 100,
    "damage": 19,
    "action_index": "attack",
    "type": 1,
    "search_condition": [
      1
    ],
    "oxy_type": [
      1
    ],
    "id": 900434,
    "spawn_bound": "cannon",
    "barrage_ID": [
      903412
    ],
    "corrected": 105,
    "auto_aftercast": 0,
    "bullet_ID": [
      900431
    ],
    "min_range": 0,
    "initial_over_heat": 0,
    "aim_type": 0,
    "fire_sfx": "battle/cannon-155mm",
    "effect_move": 0,
    "axis_angle": 0
  },
  "950133": {
    "search_type": 1,
    "attack_attribute": 1,
    "shakescreen": 0,
    "angle": 180,
    "reload_max": 700,
    "torpedo_ammo": 0,
    "queue": 4,
    "name": "【挑战关卡7】提尔比茨_爆炸圈",
    "fire_fx": "CAFire",
    "charge_param": "",
    "suppress": 1,
    "range": 90,
    "recover_time": 0,
    "fire_fx_loop_type": 1,
    "precast_param": [],
    "expose": 0,
    "attack_attribute_ratio": 100,
    "damage": 13,
    "action_index": "attack",
    "type": 1,
    "search_condition": [
      1
    ],
    "oxy_type": [
      1
    ],
    "id": 950133,
    "spawn_bound": "cannon",
    "barrage_ID": [
      950105,
      950106
    ],
    "corrected": 100,
    "auto_aftercast": 0,
    "bullet_ID": [
      470351,
      470352
    ],
    "min_range": 0,
    "initial_over_heat": 0,
    "aim_type": 0,
    "fire_sfx": "battle/cannon-main",
    "effect_move": 0,
    "axis_angle": 0
  },
  "940062": {
    "search_type": 1,
    "attack_attribute": 1,
    "shakescreen": 0,
    "angle": 360,
    "reload_max": 600,
    "torpedo_ammo": 0,
    "queue": 1,
    "name": "【挑战关卡5】绫波_近程自卫火炮II",
    "fire_fx": "CLFire",
    "charge_param": "",
    "suppress": 1,
    "range": 38,
    "recover_time": 0.5,
    "fire_fx_loop_type": 1,
    "precast_param": [],
    "expose": 0,
    "attack_attribute_ratio": 100,
    "damage": 19,
    "action_index": "attack",
    "type": 2,
    "search_condition": [
      1
    ],
    "oxy_type": [
      1
    ],
    "id": 940062,
    "spawn_bound": "cannon",
    "barrage_ID": [
      12
    ],
    "corrected": 125,
    "auto_aftercast": 0,
    "bullet_ID": [
      999
    ],
    "min_range": 0,
    "initial_over_heat": 0,
    "aim_type": 1,
    "fire_sfx": "battle/cannon-155mm",
    "effect_move": 0,
    "axis_angle": 0
  },
  "900341": {
    "search_type": 1,
    "attack_attribute": 1,
    "shakescreen": 0,
    "angle": 360,
    "reload_max": 500,
    "torpedo_ammo": 0,
    "queue": 9,
    "name": "【挑战关卡3】2连跨射炮",
    "fire_fx": "CLFire",
    "charge_param": "",
    "suppress": 1,
    "range": 90,
    "recover_time": 0,
    "fire_fx_loop_type": 3,
    "precast_param": [],
    "expose": 0,
    "attack_attribute_ratio": 100,
    "damage": 19,
    "action_index": "attack",
    "type": 1,
    "search_condition": [
      1
    ],
    "oxy_type": [
      1
    ],
    "id": 900341,
    "spawn_bound": "cannon",
    "barrage_ID": [
      900341
    ],
    "corrected": 105,
    "auto_aftercast": 0,
    "bullet_ID": [
      900341
    ],
    "min_range": 0,
    "initial_over_heat": 0,
    "aim_type": 1,
    "fire_sfx": "battle/cannon-155mm",
    "effect_move": 0,
    "axis_angle": 0
  },
  "950131": {
    "search_type": 1,
    "attack_attribute": 1,
    "shakescreen": 0,
    "angle": 180,
    "reload_max": 500,
    "torpedo_ammo": 0,
    "queue": 2,
    "name": "【挑战关卡7】提尔比茨_爆炸圈",
    "fire_fx": "CAFire",
    "charge_param": "",
    "suppress": 1,
    "range": 90,
    "recover_time": 0,
    "fire_fx_loop_type": 1,
    "precast_param": [],
    "expose": 0,
    "attack_attribute_ratio": 100,
    "damage": 13,
    "action_index": "attack",
    "type": 1,
    "search_condition": [
      1
    ],
    "oxy_type": [
      1
    ],
    "id": 950131,
    "spawn_bound": "cannon",
    "barrage_ID": [
      950101,
      950102
    ],
    "corrected": 100,
    "auto_aftercast": 0,
    "bullet_ID": [
      470331,
      470332
    ],
    "min_range": 0,
    "initial_over_heat": 0,
    "aim_type": 0,
    "fire_sfx": "battle/cannon-main",
    "effect_move": 0,
    "axis_angle": 0
  },
  "950112": {
    "search_type": 1,
    "attack_attribute": 1,
    "shakescreen": 0,
    "angle": 360,
    "reload_max": 500,
    "torpedo_ammo": 0,
    "queue": 2,
    "name": "【挑战关卡6】天城          Q版近程自卫火炮III",
    "fire_fx": "CLFire",
    "charge_param": "",
    "suppress": 1,
    "range": 38,
    "recover_time": 0.5,
    "fire_fx_loop_type": 1,
    "precast_param": [],
    "expose": 0,
    "attack_attribute_ratio": 100,
    "damage": 20,
    "action_index": "attack",
    "type": 2,
    "search_condition": [
      1
    ],
    "oxy_type": [
      1
    ],
    "id": 950112,
    "spawn_bound": "cannon",
    "barrage_ID": [
      13
    ],
    "corrected": 125,
    "auto_aftercast": 0,
    "bullet_ID": [
      999
    ],
    "min_range": 0,
    "initial_over_heat": 0,
    "aim_type": 1,
    "fire_sfx": "battle/cannon-155mm",
    "effect_move": 0,
    "axis_angle": 0
  },
  "900437": {
    "search_type": 1,
    "attack_attribute": 1,
    "shakescreen": 0,
    "angle": 360,
    "reload_max": 500,
    "torpedo_ammo": 0,
    "queue": 9,
    "name": "【挑战关卡4】波浪分岔_上",
    "fire_fx": "CLFire",
    "charge_param": "",
    "suppress": 1,
    "range": 90,
    "recover_time": 0,
    "fire_fx_loop_type": 3,
    "precast_param": [],
    "expose": 0,
    "attack_attribute_ratio": 100,
    "damage": 19,
    "action_index": "attack",
    "type": 1,
    "search_condition": [
      1
    ],
    "oxy_type": [
      1
    ],
    "id": 900437,
    "spawn_bound": "cannon",
    "barrage_ID": [
      903431,
      903432,
      903433,
      903434,
      903435,
      903436,
      903437,
      903438
    ],
    "corrected": 105,
    "auto_aftercast": 0,
    "bullet_ID": [
      900437,
      900437,
      900437,
      900437,
      900438,
      900438,
      900438,
      900438
    ],
    "min_range": 0,
    "initial_over_heat": 0,
    "aim_type": 0,
    "fire_sfx": "battle/cannon-155mm",
    "effect_move": 0,
    "axis_angle": 0
  },
  "900091": {
    "search_type": 1,
    "attack_attribute": 2,
    "shakescreen": 0,
    "angle": 360,
    "reload_max": 300,
    "torpedo_ammo": 0,
    "queue": 3,
    "name": "【挑战关卡4】鱼雷_单发",
    "fire_fx": "",
    "charge_param": "",
    "suppress": 1,
    "range": 90,
    "recover_time": 0,
    "fire_fx_loop_type": 1,
    "precast_param": [],
    "expose": 0,
    "attack_attribute_ratio": 100,
    "damage": 19,
    "action_index": "attack",
    "type": 3,
    "search_condition": [
      1
    ],
    "oxy_type": [
      1
    ],
    "id": 900091,
    "spawn_bound": "torpedo",
    "barrage_ID": [
      900091
    ],
    "corrected": 100,
    "auto_aftercast": 0,
    "bullet_ID": [
      900091
    ],
    "min_range": 0,
    "initial_over_heat": 0,
    "aim_type": 1,
    "fire_sfx": "",
    "effect_move": 0,
    "axis_angle": 0
  },
  "900438": {
    "search_type": 1,
    "attack_attribute": 1,
    "shakescreen": 0,
    "angle": 360,
    "reload_max": 500,
    "torpedo_ammo": 0,
    "queue": 10,
    "name": "【挑战关卡4】波浪分岔_下",
    "fire_fx": "CLFire",
    "charge_param": "",
    "suppress": 1,
    "range": 90,
    "recover_time": 0,
    "fire_fx_loop_type": 3,
    "precast_param": [],
    "expose": 0,
    "attack_attribute_ratio": 100,
    "damage": 19,
    "action_index": "attack",
    "type": 1,
    "search_condition": [
      1
    ],
    "oxy_type": [
      1
    ],
    "id": 900438,
    "spawn_bound": "cannon",
    "barrage_ID": [
      903441,
      903442,
      903443,
      903444,
      903445,
      903446,
      903447,
      903448
    ],
    "corrected": 105,
    "auto_aftercast": 0,
    "bullet_ID": [
      900437,
      900437,
      900437,
      900437,
      900438,
      900438,
      900438,
      900438
    ],
    "min_range": 0,
    "initial_over_heat": 0,
    "aim_type": 0,
    "fire_sfx": "battle/cannon-155mm",
    "effect_move": 0,
    "axis_angle": 0
  },
  "950114": {
    "search_type": 1,
    "attack_attribute": 1,
    "shakescreen": 0,
    "angle": 360,
    "reload_max": 900,
    "torpedo_ammo": 0,
    "queue": 1,
    "name": "【挑战关卡6】天城         旋转副炮",
    "fire_fx": "CLFire",
    "charge_param": "",
    "suppress": 1,
    "range": 90,
    "recover_time": 0,
    "fire_fx_loop_type": 3,
    "precast_param": [],
    "expose": 0,
    "attack_attribute_ratio": 100,
    "damage": 13,
    "action_index": "attack",
    "type": 1,
    "search_condition": [
      1
    ],
    "oxy_type": [
      1
    ],
    "id": 950114,
    "spawn_bound": "cannon",
    "barrage_ID": [
      568421,
      568422,
      568423,
      568424,
      568425,
      568426,
      568427,
      568428
    ],
    "corrected": 105,
    "auto_aftercast": 0,
    "bullet_ID": [
      568421,
      568421,
      568421,
      568421,
      568421,
      568421,
      568421,
      568421
    ],
    "min_range": 0,
    "initial_over_heat": 0,
    "aim_type": 0,
    "fire_sfx": "battle/cannon-155mm",
    "effect_move": 0,
    "axis_angle": 0
  },
  "950130": {
    "search_type": 1,
    "attack_attribute": 1,
    "shakescreen": 0,
    "angle": 360,
    "reload_max": 500,
    "torpedo_ammo": 0,
    "queue": 1,
    "name": "【挑战关卡7】提尔比茨_Q版近程自卫火炮III",
    "fire_fx": "CLFire",
    "charge_param": "",
    "suppress": 1,
    "range": 38,
    "recover_time": 0.5,
    "fire_fx_loop_type": 1,
    "precast_param": [],
    "expose": 0,
    "attack_attribute_ratio": 100,
    "damage": 20,
    "action_index": "attack",
    "type": 2,
    "search_condition": [
      1
    ],
    "oxy_type": [
      1
    ],
    "id": 950130,
    "spawn_bound": "cannon",
    "barrage_ID": [
      13
    ],
    "corrected": 125,
    "auto_aftercast": 0,
    "bullet_ID": [
      999
    ],
    "min_range": 0,
    "initial_over_heat": 0,
    "aim_type": 1,
    "fire_sfx": "battle/cannon-155mm",
    "effect_move": 0,
    "axis_angle": 0
  },
  "950115": {
    "search_type": 1,
    "attack_attribute": 1,
    "shakescreen": 0,
    "angle": 360,
    "reload_max": 99999,
    "torpedo_ammo": 0,
    "queue": 2,
    "name": "【挑战关卡6】天城         限位追踪武器",
    "fire_fx": "CAFire",
    "charge_param": "",
    "suppress": 1,
    "range": 100,
    "recover_time": 0,
    "fire_fx_loop_type": 1,
    "precast_param": [],
    "expose": 0,
    "attack_attribute_ratio": 100,
    "damage": 12,
    "action_index": "attack",
    "type": 1,
    "search_condition": [
      1
    ],
    "oxy_type": [
      1
    ],
    "id": 950115,
    "spawn_bound": "cannon",
    "barrage_ID": [
      9166,
      9167,
      9168,
      9169,
      9170,
      9171,
      9172,
      9173,
      9174,
      9175,
      9176,
      9177,
      9178,
      9179,
      9180,
      9181
    ],
    "corrected": 100,
    "auto_aftercast": 0,
    "bullet_ID": [
      9102,
      9102,
      9102,
      9102,
      9102,
      9102,
      9102,
      9102,
      9102,
      9102,
      9102,
      9102,
      9102,
      9102,
      9102,
      9102
    ],
    "min_range": 0,
    "initial_over_heat": 0,
    "aim_type": 1,
    "fire_sfx": "battle/cannon-main",
    "effect_move": 0,
    "axis_angle": 0
  },
  "900692": {
    "search_type": 1,
    "attack_attribute": 1,
    "shakescreen": 0,
    "angle": 360,
    "reload_max": 400,
    "torpedo_ammo": 0,
    "queue": 9,
    "name": "【挑战关卡3】自机狙_4面_不可避",
    "fire_fx": "CLFire",
    "charge_param": "",
    "suppress": 1,
    "range": 90,
    "recover_time": 0,
    "fire_fx_loop_type": 3,
    "precast_param": [],
    "expose": 0,
    "attack_attribute_ratio": 100,
    "damage": 19,
    "action_index": "attack",
    "type": 1,
    "search_condition": [
      1
    ],
    "oxy_type": [
      1
    ],
    "id": 900692,
    "spawn_bound": "cannon",
    "barrage_ID": [
      901671,
      901672,
      901673,
      901674,
      901675,
      901676,
      901677,
      901678
    ],
    "corrected": 105,
    "auto_aftercast": 0,
    "bullet_ID": [
      900691,
      900691,
      900691,
      900691,
      900691,
      900691,
      900691,
      900691
    ],
    "min_range": 0,
    "initial_over_heat": 0,
    "aim_type": 0,
    "fire_sfx": "battle/cannon-155mm",
    "effect_move": 0,
    "axis_angle": 0
  },
  "950116": {
    "search_type": 1,
    "attack_attribute": 1,
    "shakescreen": 0,
    "angle": 360,
    "reload_max": 600,
    "torpedo_ammo": 0,
    "queue": 1,
    "name": "【挑战关卡6】天城         旋转后回笼再飞出去",
    "fire_fx": "CLFire",
    "charge_param": "",
    "suppress": 1,
    "range": 90,
    "recover_time": 0,
    "fire_fx_loop_type": 3,
    "precast_param": [],
    "expose": 0,
    "attack_attribute_ratio": 100,
    "damage": 12,
    "action_index": "attack",
    "type": 1,
    "search_condition": [
      1
    ],
    "oxy_type": [
      1
    ],
    "id": 950116,
    "spawn_bound": "cannon",
    "barrage_ID": [
      990321
    ],
    "corrected": 105,
    "auto_aftercast": 0,
    "bullet_ID": [
      600700
    ],
    "min_range": 0,
    "initial_over_heat": 0,
    "aim_type": 0,
    "fire_sfx": "battle/cannon-155mm",
    "effect_move": 0,
    "axis_angle": 0
  },
  "950111": {
    "search_type": 1,
    "attack_attribute": 1,
    "shakescreen": 0,
    "angle": 360,
    "reload_max": 450,
    "torpedo_ammo": 0,
    "queue": 1,
    "name": "【挑战关卡6】天城         环绕多层",
    "fire_fx": "CLFire",
    "charge_param": "",
    "suppress": 1,
    "range": 90,
    "recover_time": 0,
    "fire_fx_loop_type": 3,
    "precast_param": [],
    "expose": 0,
    "attack_attribute_ratio": 100,
    "damage": 10,
    "action_index": "attack",
    "type": 1,
    "search_condition": [
      1
    ],
    "oxy_type": [
      1
    ],
    "id": 950111,
    "spawn_bound": "cannon",
    "barrage_ID": [
      920061
    ],
    "corrected": 105,
    "auto_aftercast": 0,
    "bullet_ID": [
      920062
    ],
    "min_range": 0,
    "initial_over_heat": 0,
    "aim_type": 1,
    "fire_sfx": "battle/cannon-155mm",
    "effect_move": 0,
    "axis_angle": 0
  },
  "950117": {
    "search_type": 1,
    "attack_attribute": 1,
    "shakescreen": 0,
    "angle": 360,
    "reload_max": 1750,
    "torpedo_ammo": 0,
    "queue": 2,
    "name": "【挑战关卡6】天城         1排 上中下三路慢速弹幕 第2阶段 ",
    "fire_fx": "CLFire",
    "charge_param": "",
    "suppress": 1,
    "range": 90,
    "recover_time": 0,
    "fire_fx_loop_type": 3,
    "precast_param": [],
    "expose": 0,
    "attack_attribute_ratio": 100,
    "damage": 30,
    "action_index": "attack",
    "type": 1,
    "search_condition": [
      1
    ],
    "oxy_type": [
      1
    ],
    "id": 950117,
    "spawn_bound": "cannon",
    "barrage_ID": [
      595031,
      595032,
      595033
    ],
    "corrected": 105,
    "auto_aftercast": 0,
    "bullet_ID": [
      600701,
      600701,
      600701
    ],
    "min_range": 0,
    "initial_over_heat": 0,
    "aim_type": 0,
    "fire_sfx": "battle/cannon-155mm",
    "effect_move": 0,
    "axis_angle": 0
  },
  "950113": {
    "search_type": 1,
    "attack_attribute": 1,
    "shakescreen": 0,
    "angle": 360,
    "reload_max": 2400,
    "torpedo_ammo": 0,
    "queue": 3,
    "name": "【挑战关卡6】天城         跨射6连",
    "fire_fx": "CAFire",
    "charge_param": "",
    "suppress": 0,
    "range": 150,
    "recover_time": 0,
    "fire_fx_loop_type": 1,
    "precast_param": [],
    "expose": 0,
    "attack_attribute_ratio": 100,
    "damage": 35,
    "action_index": "attack",
    "type": 1,
    "search_condition": [
      1
    ],
    "oxy_type": [
      1
    ],
    "id": 950113,
    "spawn_bound": "cannon",
    "barrage_ID": [
      568441
    ],
    "corrected": 80,
    "auto_aftercast": 0,
    "bullet_ID": [
      1501
    ],
    "min_range": 85,
    "initial_over_heat": 0,
    "aim_type": 1,
    "fire_sfx": "battle/cannon-main",
    "effect_move": 0,
    "axis_angle": 0
  },
  "950118": {
    "search_type": 1,
    "attack_attribute": 1,
    "shakescreen": 0,
    "angle": 360,
    "reload_max": 1750,
    "torpedo_ammo": 0,
    "queue": 4,
    "name": "【挑战关卡6】天城         2排上下二路慢速弹幕 第2阶段 ",
    "fire_fx": "CAFire",
    "charge_param": "",
    "suppress": 1,
    "range": 90,
    "recover_time": 0,
    "fire_fx_loop_type": 1,
    "precast_param": [],
    "expose": 0,
    "attack_attribute_ratio": 100,
    "damage": 30,
    "action_index": "attack",
    "type": 1,
    "search_condition": [
      1
    ],
    "oxy_type": [
      1
    ],
    "id": 950118,
    "spawn_bound": "cannon",
    "barrage_ID": [
      595041,
      595042
    ],
    "corrected": 105,
    "auto_aftercast": 0,
    "bullet_ID": [
      600701,
      600701
    ],
    "min_range": 0,
    "initial_over_heat": 0,
    "aim_type": 0,
    "fire_sfx": "battle/cannon-155mm",
    "effect_move": 0,
    "axis_angle": 0
  },
  "900191": {
    "search_type": 1,
    "attack_attribute": 1,
    "shakescreen": 0,
    "angle": 360,
    "reload_max": 600,
    "torpedo_ammo": 0,
    "queue": 4,
    "name": "【长门陆奥】萤火虫",
    "fire_fx": "CLFire",
    "charge_param": "",
    "suppress": 1,
    "range": 90,
    "recover_time": 0,
    "fire_fx_loop_type": 3,
    "precast_param": [],
    "expose": 0,
    "attack_attribute_ratio": 100,
    "damage": 19,
    "action_index": "attack",
    "type": 1,
    "search_condition": [
      1
    ],
    "oxy_type": [
      1
    ],
    "id": 900191,
    "spawn_bound": "cannon",
    "barrage_ID": [
      900191
    ],
    "corrected": 105,
    "auto_aftercast": 0,
    "bullet_ID": [
      900191
    ],
    "min_range": 0,
    "initial_over_heat": 0,
    "aim_type": 1,
    "fire_sfx": "battle/cannon-155mm",
    "effect_move": 0,
    "axis_angle": 0
  },
  "950119": {
    "search_type": 2,
    "attack_attribute": 1,
    "shakescreen": 0,
    "angle": 360,
    "reload_max": 2400,
    "torpedo_ammo": 0,
    "queue": 2,
    "name": "【挑战关卡6】天城         特殊弹幕（鱼雷",
    "fire_fx": "",
    "charge_param": "",
    "suppress": 1,
    "range": 60,
    "recover_time": 0.5,
    "fire_fx_loop_type": 1,
    "precast_param": [],
    "expose": 0,
    "attack_attribute_ratio": 100,
    "damage": 20,
    "action_index": "attack",
    "type": 3,
    "search_condition": [
      1
    ],
    "oxy_type": [
      1
    ],
    "id": 950119,
    "spawn_bound": "torpedo",
    "barrage_ID": [
      110608,
      110609
    ],
    "corrected": 125,
    "auto_aftercast": 0,
    "bullet_ID": [
      110605,
      110606
    ],
    "min_range": 0,
    "initial_over_heat": 0,
    "aim_type": 1,
    "fire_sfx": "",
    "effect_move": 0,
    "axis_angle": 0
  },
  "940071": {
    "search_type": 1,
    "attack_attribute": 1,
    "shakescreen": 0,
    "angle": 360,
    "reload_max": 300,
    "torpedo_ammo": 0,
    "queue": 1,
    "name": "【长门陆奥】爆炸圆_快",
    "fire_fx": "CLFire",
    "charge_param": "",
    "suppress": 1,
    "range": 90,
    "recover_time": 0,
    "fire_fx_loop_type": 3,
    "precast_param": [],
    "expose": 0,
    "attack_attribute_ratio": 100,
    "damage": 19,
    "action_index": "attack",
    "type": 1,
    "search_condition": [
      1
    ],
    "oxy_type": [
      1
    ],
    "id": 940071,
    "spawn_bound": "cannon",
    "barrage_ID": [
      940071,
      940072,
      940073,
      940074,
      940075,
      940076
    ],
    "corrected": 105,
    "auto_aftercast": 0,
    "bullet_ID": [
      940071,
      940071,
      940071,
      940074,
      940074,
      940074
    ],
    "min_range": 0,
    "initial_over_heat": 0,
    "aim_type": 1,
    "fire_sfx": "battle/cannon-155mm",
    "effect_move": 0,
    "axis_angle": 0
  },
  "950120": {
    "search_type": 1,
    "attack_attribute": 1,
    "shakescreen": 0,
    "angle": 360,
    "reload_max": 100,
    "torpedo_ammo": 0,
    "queue": 5,
    "name": "【挑战关卡6】天城         12颗炮弹2轮攻击前排",
    "fire_fx": "CAFire",
    "charge_param": "",
    "suppress": 1,
    "range": 60,
    "recover_time": 0,
    "fire_fx_loop_type": 1,
    "precast_param": {
      "alertTime": 2,
      "fx": "jinengenemy",
      "time": 1,
      "isBound": true
    },
    "expose": 0,
    "attack_attribute_ratio": 100,
    "damage": 12,
    "action_index": "attack",
    "type": 19,
    "search_condition": [
      1
    ],
    "oxy_type": [
      1
    ],
    "id": 950120,
    "spawn_bound": "cannon",
    "barrage_ID": [
      9073
    ],
    "corrected": 100,
    "auto_aftercast": 0,
    "bullet_ID": [
      399988
    ],
    "min_range": 20,
    "initial_over_heat": 0,
    "aim_type": 1,
    "fire_sfx": "battle/cannon-main",
    "effect_move": 0,
    "axis_angle": 0
  },
  "940072": {
    "search_type": 1,
    "attack_attribute": 1,
    "shakescreen": 0,
    "angle": 360,
    "reload_max": 300,
    "torpedo_ammo": 0,
    "queue": 1,
    "name": "【长门陆奥】爆炸圆_中",
    "fire_fx": "CLFire",
    "charge_param": "",
    "suppress": 1,
    "range": 90,
    "recover_time": 0,
    "fire_fx_loop_type": 3,
    "precast_param": [],
    "expose": 0,
    "attack_attribute_ratio": 100,
    "damage": 19,
    "action_index": "attack",
    "type": 1,
    "search_condition": [
      1
    ],
    "oxy_type": [
      1
    ],
    "id": 940072,
    "spawn_bound": "cannon",
    "barrage_ID": [
      940071,
      940072,
      940073,
      940074,
      940075,
      940076
    ],
    "corrected": 105,
    "auto_aftercast": 0,
    "bullet_ID": [
      940072,
      940072,
      940072,
      940075,
      940075,
      940075
    ],
    "min_range": 0,
    "initial_over_heat": 0,
    "aim_type": 1,
    "fire_sfx": "battle/cannon-155mm",
    "effect_move": 0,
    "axis_angle": 0
  },
  "950121": {
    "search_type": 1,
    "attack_attribute": 1,
    "shakescreen": 0,
    "angle": 360,
    "reload_max": 600,
    "torpedo_ammo": 0,
    "queue": 1,
    "name": "【挑战关卡6】天城_特色",
    "fire_fx": "CLFire",
    "charge_param": "",
    "suppress": 1,
    "range": 90,
    "recover_time": 0,
    "fire_fx_loop_type": 3,
    "precast_param": [],
    "expose": 0,
    "attack_attribute_ratio": 100,
    "damage": 12,
    "action_index": "attack",
    "type": 1,
    "search_condition": [
      1
    ],
    "oxy_type": [
      1
    ],
    "id": 950121,
    "spawn_bound": "cannon",
    "barrage_ID": [
      950051,
      950052,
      950053,
      950054
    ],
    "corrected": 105,
    "auto_aftercast": 0,
    "bullet_ID": [
      950050,
      950050,
      950050,
      950050
    ],
    "min_range": 0,
    "initial_over_heat": 0,
    "aim_type": 0,
    "fire_sfx": "battle/cannon-155mm",
    "effect_move": 0,
    "axis_angle": 0
  },
  "940073": {
    "search_type": 1,
    "attack_attribute": 1,
    "shakescreen": 0,
    "angle": 360,
    "reload_max": 300,
    "torpedo_ammo": 0,
    "queue": 1,
    "name": "【长门陆奥】爆炸圆_慢",
    "fire_fx": "CLFire",
    "charge_param": "",
    "suppress": 1,
    "range": 90,
    "recover_time": 0,
    "fire_fx_loop_type": 3,
    "precast_param": [],
    "expose": 0,
    "attack_attribute_ratio": 100,
    "damage": 19,
    "action_index": "attack",
    "type": 1,
    "search_condition": [
      1
    ],
    "oxy_type": [
      1
    ],
    "id": 940073,
    "spawn_bound": "cannon",
    "barrage_ID": [
      940071,
      940072,
      940073,
      940074,
      940075,
      940076
    ],
    "corrected": 105,
    "auto_aftercast": 0,
    "bullet_ID": [
      940073,
      940073,
      940073,
      940076,
      940076,
      940076
    ],
    "min_range": 0,
    "initial_over_heat": 0,
    "aim_type": 1,
    "fire_sfx": "battle/cannon-155mm",
    "effect_move": 0,
    "axis_angle": 0
  },
  "900651": {
    "search_type": 1,
    "attack_attribute": 1,
    "shakescreen": 0,
    "angle": 360,
    "reload_max": 450,
    "torpedo_ammo": 0,
    "queue": 9,
    "name": "【长门陆奥】自机狙_单线_短",
    "fire_fx": "CLFire",
    "charge_param": "",
    "suppress": 1,
    "range": 90,
    "recover_time": 0,
    "fire_fx_loop_type": 3,
    "precast_param": [],
    "expose": 0,
    "attack_attribute_ratio": 100,
    "damage": 19,
    "action_index": "attack",
    "type": 1,
    "search_condition": [
      1
    ],
    "oxy_type": [
      1
    ],
    "id": 900651,
    "spawn_bound": "cannon",
    "barrage_ID": [
      900651
    ],
    "corrected": 105,
    "auto_aftercast": 0,
    "bullet_ID": [
      900651
    ],
    "min_range": 0,
    "initial_over_heat": 0,
    "aim_type": 1,
    "fire_sfx": "battle/cannon-155mm",
    "effect_move": 0,
    "axis_angle": 0
  },
  "940074": {
    "search_type": 1,
    "attack_attribute": 1,
    "shakescreen": 0,
    "angle": 360,
    "reload_max": 300,
    "torpedo_ammo": 0,
    "queue": 1,
    "name": "【长门陆奥】爆炸圆_合",
    "fire_fx": "CLFire",
    "charge_param": "",
    "suppress": 1,
    "range": 90,
    "recover_time": 0,
    "fire_fx_loop_type": 3,
    "precast_param": [],
    "expose": 0,
    "attack_attribute_ratio": 100,
    "damage": 19,
    "action_index": "attack",
    "type": 1,
    "search_condition": [
      1
    ],
    "oxy_type": [
      1
    ],
    "id": 940074,
    "spawn_bound": "cannon",
    "barrage_ID": [
      940071,
      940072,
      940073,
      940074,
      940075,
      940076
    ],
    "corrected": 105,
    "auto_aftercast": 0,
    "bullet_ID": [
      940071,
      940072,
      940073,
      940074,
      940075,
      940076
    ],
    "min_range": 0,
    "initial_over_heat": 0,
    "aim_type": 1,
    "fire_sfx": "battle/cannon-155mm",
    "effect_move": 0,
    "axis_angle": 0
  },
  "950097": {
    "search_type": 1,
    "attack_attribute": 2,
    "shakescreen": 0,
    "angle": 60,
    "reload_max": 500,
    "torpedo_ammo": 0,
    "queue": 1,
    "name": "【挑战关卡5】绫波_进阶鱼雷",
    "fire_fx": "",
    "charge_param": "",
    "suppress": 1,
    "range": 50,
    "recover_time": 0.5,
    "fire_fx_loop_type": 1,
    "precast_param": [],
    "expose": 0,
    "attack_attribute_ratio": 100,
    "damage": 48,
    "action_index": "attack",
    "type": 3,
    "search_condition": [
      1
    ],
    "oxy_type": [
      1
    ],
    "id": 950097,
    "spawn_bound": "torpedo",
    "barrage_ID": [
      9053,
      9054
    ],
    "corrected": 100,
    "auto_aftercast": 0,
    "bullet_ID": [
      9053,
      9054
    ],
    "min_range": 0,
    "initial_over_heat": 1,
    "aim_type": 1,
    "fire_sfx": "",
    "effect_move": 0,
    "axis_angle": 0
  },
  "950092": {
    "search_type": 1,
    "attack_attribute": 1,
    "shakescreen": 0,
    "angle": 360,
    "reload_max": 60,
    "torpedo_ammo": 0,
    "queue": 1,
    "name": "【挑战关卡5】绫波_爪击武器上",
    "fire_fx": "CAFire",
    "charge_param": "",
    "suppress": 1,
    "range": 100,
    "recover_time": 0,
    "fire_fx_loop_type": 1,
    "precast_param": [],
    "expose": 0,
    "attack_attribute_ratio": 100,
    "damage": 75,
    "action_index": "attack",
    "type": 1,
    "search_condition": [
      1
    ],
    "oxy_type": [
      1
    ],
    "id": 950092,
    "spawn_bound": "cannon",
    "barrage_ID": [
      9150,
      9151,
      9152,
      9153
    ],
    "corrected": 100,
    "auto_aftercast": 0,
    "bullet_ID": [
      9100,
      9100,
      9100,
      9100,
      9100
    ],
    "min_range": 0,
    "initial_over_heat": 0,
    "aim_type": 0,
    "fire_sfx": "battle/cannon-main",
    "effect_move": 0,
    "axis_angle": 0
  },
  "950095": {
    "search_type": 1,
    "attack_attribute": 1,
    "shakescreen": 302,
    "angle": 50,
    "reload_max": 99999,
    "torpedo_ammo": 0,
    "queue": 1,
    "name": "【挑战关卡5】绫波_限位分裂弹",
    "fire_fx": "zhupao",
    "charge_param": "",
    "suppress": 1,
    "range": 200,
    "recover_time": 0.5,
    "fire_fx_loop_type": 1,
    "precast_param": [],
    "expose": 0,
    "attack_attribute_ratio": 100,
    "damage": 12,
    "action_index": "attack",
    "type": 1,
    "search_condition": [
      1
    ],
    "oxy_type": [
      1
    ],
    "id": 950095,
    "spawn_bound": "cannon",
    "barrage_ID": [
      9158,
      9159,
      9160,
      9161,
      9162,
      9163,
      9164,
      9165
    ],
    "corrected": 110,
    "auto_aftercast": 0,
    "bullet_ID": [
      9103,
      9104,
      9104,
      9104,
      9103,
      9104,
      9104,
      9104
    ],
    "min_range": 50,
    "initial_over_heat": 1,
    "aim_type": 0,
    "fire_sfx": "battle/cannon-main",
    "effect_move": 0,
    "axis_angle": 0
  },
  "900701": {
    "search_type": 1,
    "attack_attribute": 1,
    "shakescreen": 0,
    "angle": 360,
    "reload_max": 250,
    "torpedo_ammo": 0,
    "queue": 10,
    "name": "【挑战关卡3】自机狙_散布_慢",
    "fire_fx": "CLFire",
    "charge_param": "",
    "suppress": 1,
    "range": 90,
    "recover_time": 0,
    "fire_fx_loop_type": 3,
    "precast_param": [],
    "expose": 0,
    "attack_attribute_ratio": 100,
    "damage": 19,
    "action_index": "attack",
    "type": 1,
    "search_condition": [
      1
    ],
    "oxy_type": [
      1
    ],
    "id": 900701,
    "spawn_bound": "cannon",
    "barrage_ID": [
      900645
    ],
    "corrected": 105,
    "auto_aftercast": 0,
    "bullet_ID": [
      900611
    ],
    "min_range": 0,
    "initial_over_heat": 0,
    "aim_type": 0,
    "fire_sfx": "battle/cannon-155mm",
    "effect_move": 0,
    "axis_angle": 0
  },
  "950094": {
    "search_type": 1,
    "attack_attribute": 1,
    "shakescreen": 0,
    "angle": 360,
    "reload_max": 99999,
    "torpedo_ammo": 0,
    "queue": 2,
    "name": "【挑战关卡5】绫波_限位追踪武器",
    "fire_fx": "CAFire",
    "charge_param": "",
    "suppress": 1,
    "range": 100,
    "recover_time": 0,
    "fire_fx_loop_type": 1,
    "precast_param": [],
    "expose": 0,
    "attack_attribute_ratio": 100,
    "damage": 75,
    "action_index": "attack",
    "type": 1,
    "search_condition": [
      1
    ],
    "oxy_type": [
      1
    ],
    "id": 950094,
    "spawn_bound": "cannon",
    "barrage_ID": [
      9166,
      9167,
      9168,
      9169,
      9170,
      9171,
      9172,
      9173
    ],
    "corrected": 100,
    "auto_aftercast": 0,
    "bullet_ID": [
      9102,
      9102,
      9102,
      9102,
      9102,
      9102,
      9102,
      9102
    ],
    "min_range": 0,
    "initial_over_heat": 0,
    "aim_type": 1,
    "fire_sfx": "battle/cannon-main",
    "effect_move": 0,
    "axis_angle": 0
  },
  "900702": {
    "search_type": 1,
    "attack_attribute": 1,
    "shakescreen": 0,
    "angle": 360,
    "reload_max": 250,
    "torpedo_ammo": 0,
    "queue": 10,
    "name": "【挑战关卡3】自机狙_散布_快慢",
    "fire_fx": "CLFire",
    "charge_param": "",
    "suppress": 1,
    "range": 90,
    "recover_time": 0,
    "fire_fx_loop_type": 3,
    "precast_param": [],
    "expose": 0,
    "attack_attribute_ratio": 100,
    "damage": 19,
    "action_index": "attack",
    "type": 1,
    "search_condition": [
      1
    ],
    "oxy_type": [
      1
    ],
    "id": 900702,
    "spawn_bound": "cannon",
    "barrage_ID": [
      900645,
      900646
    ],
    "corrected": 105,
    "auto_aftercast": 0,
    "bullet_ID": [
      900611,
      900601
    ],
    "min_range": 0,
    "initial_over_heat": 0,
    "aim_type": 0,
    "fire_sfx": "battle/cannon-155mm",
    "effect_move": 0,
    "axis_angle": 0
  },
  "950093": {
    "search_type": 1,
    "attack_attribute": 1,
    "shakescreen": 0,
    "angle": 360,
    "reload_max": 60,
    "torpedo_ammo": 0,
    "queue": 2,
    "name": "【挑战关卡5】绫波_爪击武器下",
    "fire_fx": "CAFire",
    "charge_param": "",
    "suppress": 1,
    "range": 100,
    "recover_time": 0,
    "fire_fx_loop_type": 1,
    "precast_param": [],
    "expose": 0,
    "attack_attribute_ratio": 100,
    "damage": 75,
    "action_index": "attack",
    "type": 1,
    "search_condition": [
      1
    ],
    "oxy_type": [
      1
    ],
    "id": 950093,
    "spawn_bound": "cannon",
    "barrage_ID": [
      9154,
      9155,
      9156,
      9157
    ],
    "corrected": 100,
    "auto_aftercast": 0,
    "bullet_ID": [
      9101,
      9101,
      9101,
      9101,
      9101
    ],
    "min_range": 0,
    "initial_over_heat": 0,
    "aim_type": 0,
    "fire_sfx": "battle/cannon-main",
    "effect_move": 0,
    "axis_angle": 0
  },
  "900703": {
    "search_type": 1,
    "attack_attribute": 1,
    "shakescreen": 0,
    "angle": 360,
    "reload_max": 250,
    "torpedo_ammo": 0,
    "queue": 10,
    "name": "【挑战关卡3】棋子",
    "fire_fx": "CLFire",
    "charge_param": "",
    "suppress": 1,
    "range": 90,
    "recover_time": 0,
    "fire_fx_loop_type": 3,
    "precast_param": [],
    "expose": 0,
    "attack_attribute_ratio": 100,
    "damage": 19,
    "action_index": "attack",
    "type": 1,
    "search_condition": [
      1
    ],
    "oxy_type": [
      1
    ],
    "id": 900703,
    "spawn_bound": "cannon",
    "barrage_ID": [
      900647,
      900648
    ],
    "corrected": 105,
    "auto_aftercast": 0,
    "bullet_ID": [
      900612,
      900612
    ],
    "min_range": 0,
    "initial_over_heat": 0,
    "aim_type": 0,
    "fire_sfx": "battle/cannon-155mm",
    "effect_move": 0,
    "axis_angle": 0
  },
  "950091": {
    "search_type": 1,
    "attack_attribute": 1,
    "shakescreen": 0,
    "angle": 360,
    "reload_max": 625,
    "torpedo_ammo": 0,
    "queue": 1,
    "name": "【挑战关卡5】绫波_特殊武器1",
    "fire_fx": "CAFire",
    "charge_param": "",
    "suppress": 1,
    "range": 90,
    "recover_time": 0,
    "fire_fx_loop_type": 1,
    "precast_param": [],
    "expose": 0,
    "attack_attribute_ratio": 100,
    "damage": 19,
    "action_index": "attack",
    "type": 1,
    "search_condition": [
      1
    ],
    "oxy_type": [
      1
    ],
    "id": 950091,
    "spawn_bound": "cannon",
    "barrage_ID": [
      9040,
      9041
    ],
    "corrected": 100,
    "auto_aftercast": 0,
    "bullet_ID": [
      9040,
      9041
    ],
    "min_range": 0,
    "initial_over_heat": 0,
    "aim_type": 1,
    "fire_sfx": "battle/cannon-main",
    "effect_move": 0,
    "axis_angle": 0
  },
  "900704": {
    "search_type": 1,
    "attack_attribute": 1,
    "shakescreen": 0,
    "angle": 360,
    "reload_max": 600,
    "torpedo_ammo": 0,
    "queue": 1,
    "name": "【挑战关卡3】近程自卫火炮II",
    "fire_fx": "CLFire",
    "charge_param": "",
    "suppress": 1,
    "range": 38,
    "recover_time": 0.5,
    "fire_fx_loop_type": 1,
    "precast_param": [],
    "expose": 0,
    "attack_attribute_ratio": 100,
    "damage": 20,
    "action_index": "attack",
    "type": 2,
    "search_condition": [
      1
    ],
    "oxy_type": [
      1
    ],
    "id": 900704,
    "spawn_bound": "cannon",
    "barrage_ID": [
      12
    ],
    "corrected": 125,
    "auto_aftercast": 0,
    "bullet_ID": [
      999
    ],
    "min_range": 0,
    "initial_over_heat": 0,
    "aim_type": 1,
    "fire_sfx": "battle/cannon-155mm",
    "effect_move": 0,
    "axis_angle": 0
  },
  "900192": {
    "search_type": 1,
    "attack_attribute": 1,
    "shakescreen": 0,
    "angle": 360,
    "reload_max": 600,
    "torpedo_ammo": 0,
    "queue": 4,
    "name": "【长门陆奥】萤火虫*3",
    "fire_fx": "CLFire",
    "charge_param": "",
    "suppress": 1,
    "range": 90,
    "recover_time": 0,
    "fire_fx_loop_type": 3,
    "precast_param": [],
    "expose": 0,
    "attack_attribute_ratio": 100,
    "damage": 19,
    "action_index": "attack",
    "type": 1,
    "search_condition": [
      1
    ],
    "oxy_type": [
      1
    ],
    "id": 900192,
    "spawn_bound": "cannon",
    "barrage_ID": [
      900192
    ],
    "corrected": 105,
    "auto_aftercast": 0,
    "bullet_ID": [
      900191
    ],
    "min_range": 0,
    "initial_over_heat": 0,
    "aim_type": 1,
    "fire_sfx": "battle/cannon-155mm",
    "effect_move": 0,
    "axis_angle": 0
  },
  "900201": {
    "search_type": 1,
    "attack_attribute": 1,
    "shakescreen": 0,
    "angle": 360,
    "reload_max": 600,
    "torpedo_ammo": 0,
    "queue": 4,
    "name": "【挑战关卡4】小雨_随机",
    "fire_fx": "CAFire",
    "charge_param": "",
    "suppress": 1,
    "range": 90,
    "recover_time": 0,
    "fire_fx_loop_type": 1,
    "precast_param": [],
    "expose": 0,
    "attack_attribute_ratio": 80,
    "damage": 19,
    "action_index": "attack",
    "type": 1,
    "search_condition": [
      1
    ],
    "oxy_type": [
      1
    ],
    "id": 900201,
    "spawn_bound": "cannon",
    "barrage_ID": [
      900201,
      900202
    ],
    "corrected": 100,
    "auto_aftercast": 0,
    "bullet_ID": [
      900201,
      900201
    ],
    "min_range": 0,
    "initial_over_heat": 0,
    "aim_type": 0,
    "fire_sfx": "battle/cannon-main",
    "effect_move": 0,
    "axis_angle": 0
  },
  "900611": {
    "search_type": 1,
    "attack_attribute": 1,
    "shakescreen": 0,
    "angle": 360,
    "reload_max": 450,
    "torpedo_ammo": 0,
    "queue": 4,
    "name": "【长门陆奥】散布_先发后到",
    "fire_fx": "CLFire",
    "charge_param": "",
    "suppress": 1,
    "range": 90,
    "recover_time": 0,
    "fire_fx_loop_type": 3,
    "precast_param": [],
    "expose": 0,
    "attack_attribute_ratio": 100,
    "damage": 19,
    "action_index": "attack",
    "type": 1,
    "search_condition": [
      1
    ],
    "oxy_type": [
      1
    ],
    "id": 900611,
    "spawn_bound": "cannon",
    "barrage_ID": [
      900611,
      900612,
      900613
    ],
    "corrected": 105,
    "auto_aftercast": 0,
    "bullet_ID": [
      900611,
      900612,
      900613
    ],
    "min_range": 0,
    "initial_over_heat": 0,
    "aim_type": 1,
    "fire_sfx": "battle/cannon-155mm",
    "effect_move": 0,
    "axis_angle": 0
  },
  "950098": {
    "search_type": 1,
    "attack_attribute": 1,
    "shakescreen": 0,
    "angle": 360,
    "reload_max": 750,
    "torpedo_ammo": 0,
    "queue": 1,
    "name": "【挑战关卡5】绫波_特殊武器2",
    "fire_fx": "CAFire",
    "charge_param": "",
    "suppress": 1,
    "range": 90,
    "recover_time": 0,
    "fire_fx_loop_type": 1,
    "precast_param": [],
    "expose": 0,
    "attack_attribute_ratio": 100,
    "damage": 16,
    "action_index": "attack",
    "type": 1,
    "search_condition": [
      1
    ],
    "oxy_type": [
      1
    ],
    "id": 950098,
    "spawn_bound": "cannon",
    "barrage_ID": [
      9055,
      9056
    ],
    "corrected": 100,
    "auto_aftercast": 0,
    "bullet_ID": [
      9055,
      9056
    ],
    "min_range": 0,
    "initial_over_heat": 0,
    "aim_type": 0,
    "fire_sfx": "battle/cannon-main",
    "effect_move": 0,
    "axis_angle": 0
  },
  "900801": {
    "search_type": 1,
    "attack_attribute": 1,
    "shakescreen": 0,
    "angle": 360,
    "reload_max": 300,
    "torpedo_ammo": 0,
    "queue": 9,
    "name": "【挑战关卡4】刀波",
    "fire_fx": "CAFire",
    "charge_param": "",
    "suppress": 0,
    "range": 100,
    "recover_time": 0,
    "fire_fx_loop_type": 1,
    "precast_param": [],
    "expose": 0,
    "attack_attribute_ratio": 60,
    "damage": 17,
    "action_index": "attack",
    "type": 1,
    "search_condition": [
      1
    ],
    "oxy_type": [
      1
    ],
    "id": 900801,
    "spawn_bound": "cannon",
    "barrage_ID": [
      900801,
      900802
    ],
    "corrected": 100,
    "auto_aftercast": 0,
    "bullet_ID": [
      900801,
      900801
    ],
    "min_range": 0,
    "initial_over_heat": 0,
    "aim_type": 1,
    "fire_sfx": "battle/cannon-main",
    "effect_move": 0,
    "axis_angle": 0
  },
  "900112": {
    "search_type": 1,
    "attack_attribute": 1,
    "shakescreen": 0,
    "angle": 360,
    "reload_max": 600,
    "torpedo_ammo": 0,
    "queue": 1,
    "name": "【挑战关卡4】近程自卫火炮II",
    "fire_fx": "CLFire",
    "charge_param": "",
    "suppress": 1,
    "range": 38,
    "recover_time": 0.5,
    "fire_fx_loop_type": 1,
    "precast_param": [],
    "expose": 0,
    "attack_attribute_ratio": 100,
    "damage": 19,
    "action_index": "attack",
    "type": 2,
    "search_condition": [
      1
    ],
    "oxy_type": [
      1
    ],
    "id": 900112,
    "spawn_bound": "cannon",
    "barrage_ID": [
      12
    ],
    "corrected": 125,
    "auto_aftercast": 0,
    "bullet_ID": [
      999
    ],
    "min_range": 0,
    "initial_over_heat": 0,
    "aim_type": 1,
    "fire_sfx": "battle/cannon-155mm",
    "effect_move": 0,
    "axis_angle": 0
  },
  "900802": {
    "search_type": 1,
    "attack_attribute": 1,
    "shakescreen": 0,
    "angle": 360,
    "reload_max": 150,
    "torpedo_ammo": 0,
    "queue": 9,
    "name": "【挑战关卡4】刀波_高频率",
    "fire_fx": "CAFire",
    "charge_param": "",
    "suppress": 0,
    "range": 100,
    "recover_time": 0,
    "fire_fx_loop_type": 1,
    "precast_param": [],
    "expose": 0,
    "attack_attribute_ratio": 60,
    "damage": 17,
    "action_index": "attack",
    "type": 1,
    "search_condition": [
      1
    ],
    "oxy_type": [
      1
    ],
    "id": 900802,
    "spawn_bound": "cannon",
    "barrage_ID": [
      900801,
      900802
    ],
    "corrected": 100,
    "auto_aftercast": 0,
    "bullet_ID": [
      900801,
      900801
    ],
    "min_range": 0,
    "initial_over_heat": 0,
    "aim_type": 1,
    "fire_sfx": "battle/cannon-main",
    "effect_move": 0,
    "axis_angle": 0
  },
  "940061": {
    "search_type": 1,
    "attack_attribute": 1,
    "shakescreen": 0,
    "angle": 360,
    "reload_max": 1000,
    "torpedo_ammo": 0,
    "queue": 1,
    "name": "【长门陆奥】自机狙_单线_短",
    "fire_fx": "CLFire",
    "charge_param": "",
    "suppress": 1,
    "range": 90,
    "recover_time": 0,
    "fire_fx_loop_type": 3,
    "precast_param": [],
    "expose": 0,
    "attack_attribute_ratio": 100,
    "damage": 19,
    "action_index": "attack",
    "type": 1,
    "search_condition": [
      1
    ],
    "oxy_type": [
      1
    ],
    "id": 940061,
    "spawn_bound": "cannon",
    "barrage_ID": [
      940061
    ],
    "corrected": 105,
    "auto_aftercast": 0,
    "bullet_ID": [
      940061
    ],
    "min_range": 0,
    "initial_over_heat": 0,
    "aim_type": 1,
    "fire_sfx": "battle/cannon-155mm",
    "effect_move": 0,
    "axis_angle": 0
  }
}