{
  "1": {
    "effect_list": [
      {
        "trigger": [
          "onAttach",
          "onRemove"
        ],
        "type": "BattleBuffAddAttr",
        "arg_list": {
          "attr": "antiAirPower",
          "number": 20
        }
      }
    ]
  },
  "2": {
    "effect_list": [
      {
        "trigger": [
          "onAttach",
          "onRemove"
        ],
        "type": "BattleBuffAddAttr",
        "arg_list": {
          "attr": "antiAirPower",
          "number": 23
        }
      }
    ]
  },
  "3": {
    "effect_list": [
      {
        "trigger": [
          "onAttach",
          "onRemove"
        ],
        "type": "BattleBuffAddAttr",
        "arg_list": {
          "attr": "antiAirPower",
          "number": 26
        }
      }
    ]
  },
  "4": {
    "effect_list": [
      {
        "trigger": [
          "onAttach",
          "onRemove"
        ],
        "type": "BattleBuffAddAttr",
        "arg_list": {
          "attr": "antiAirPower",
          "number": 30
        }
      }
    ]
  },
  "5": {
    "effect_list": [
      {
        "trigger": [
          "onAttach",
          "onRemove"
        ],
        "type": "BattleBuffAddAttr",
        "arg_list": {
          "attr": "antiAirPower",
          "number": 33
        }
      }
    ]
  },
  "6": {
    "effect_list": [
      {
        "trigger": [
          "onAttach",
          "onRemove"
        ],
        "type": "BattleBuffAddAttr",
        "arg_list": {
          "attr": "antiAirPower",
          "number": 36
        }
      }
    ]
  },
  "7": {
    "effect_list": [
      {
        "trigger": [
          "onAttach",
          "onRemove"
        ],
        "type": "BattleBuffAddAttr",
        "arg_list": {
          "attr": "antiAirPower",
          "number": 40
        }
      }
    ]
  },
  "8": {
    "effect_list": [
      {
        "trigger": [
          "onAttach",
          "onRemove"
        ],
        "type": "BattleBuffAddAttr",
        "arg_list": {
          "attr": "antiAirPower",
          "number": 43
        }
      }
    ]
  },
  "9": {
    "effect_list": [
      {
        "trigger": [
          "onAttach",
          "onRemove"
        ],
        "type": "BattleBuffAddAttr",
        "arg_list": {
          "attr": "antiAirPower",
          "number": 46
        }
      }
    ]
  },
  "10": {
    "effect_list": [
      {
        "trigger": [
          "onAttach",
          "onRemove"
        ],
        "type": "BattleBuffAddAttr",
        "arg_list": {
          "attr": "antiAirPower",
          "number": 50
        }
      }
    ]
  },
  "picture": "",
  "color": "yellow",
  "id": 5113,
  "desc": "提高防空属性",
  "blink": [
    0,
    0.7,
    1,
    0.3,
    0.3
  ],
  "last_effect": "",
  "time": 0,
  "icon": 5110,
  "effect_list": [
    {
      "trigger": [
        "onAttach",
        "onRemove"
      ],
      "type": "BattleBuffAddAttr",
      "arg_list": {
        "attr": "antiAirPower",
        "number": 20
      }
    }
  ],
  "stack": 1,
  "init_effect": "jinengchufared",
  "name": "航空辅助"
}