{
  "10031005": {
    "smoke": [
      [
        70,
        [
          [
            "smoke",
            [
              1.035,
              0.869,
              0.099
            ]
          ]
        ]
      ],
      [
        40,
        [
          [
            "smoke",
            [
              -0.964,
              1.16,
              -0.022
            ]
          ]
        ]
      ]
    ],
    "torpedo_growth": 1296,
    "speed_growth": 0,
    "dodge": 0,
    "armor": 0,
    "antisub_growth": 0,
    "hit_growth": 120,
    "air": 0,
    "cannon": 7,
    "antiaircraft": 17,
    "reload": 150,
    "hit": 8,
    "durability": 240,
    "air_growth": 0,
    "reload_growth": 0,
    "bound_bone": {
      "antiaircraft": [
        [
          1.77,
          1.29,
          0
        ]
      ],
      "cannon": [
        [
          1.77,
          1.29,
          0
        ]
      ],
      "torpedo": [
        [
          1.17,
          0.35,
          0
        ]
      ]
    },
    "antisub": 0,
    "appear_fx": [
      "appearsmall"
    ],
    "battle_unit_type": 25,
    "luck_growth": 0,
    "star": 2,
    "antiaircraft_growth": 1440,
    "torpedo": 16,
    "equipment_list": [
      400056,
      100427
    ],
    "id": 10031005,
    "durability_growth": 9200,
    "cannon_growth": 540,
    "armor_growth": 0,
    "pilot_ai_template_id": 20005,
    "prefab": "changliangdanchuan",
    "luck": 0,
    "speed": 15,
    "base": 109,
    "rarity": 1,
    "icon": "changliangdanchuan",
    "dodge_growth": 0
  },
  "10031006": {
    "durability": 260,
    "armor": 0,
    "appear_fx": [
      "appearsmall"
    ],
    "air_growth": 0,
    "reload_growth": 0,
    "equipment_list": [
      400056,
      450052
    ],
    "antisub": 0,
    "antiaircraft_growth": 1440,
    "torpedo_growth": 1296,
    "luck": 0,
    "speed_growth": 0,
    "dodge": 0,
    "luck_growth": 0,
    "star": 2,
    "base": 110,
    "torpedo": 16,
    "air": 0,
    "battle_unit_type": 25,
    "cannon": 7,
    "hit_growth": 120,
    "id": 10031006,
    "speed": 15,
    "cannon_growth": 540,
    "reload": 150,
    "antiaircraft": 17,
    "durability_growth": 9600,
    "armor_growth": 0,
    "hit": 8,
    "rarity": 1,
    "antisub_growth": 0,
    "dodge_growth": 0,
    "pilot_ai_template_id": 20005
  },
  "10031014": {
    "durability": 790,
    "armor": 0,
    "appear_fx": [
      "appearQ"
    ],
    "air_growth": 0,
    "reload_growth": 0,
    "equipment_list": [
      100242,
      100342,
      316504,
      316505,
      316506
    ],
    "antisub": 0,
    "antiaircraft_growth": 1638,
    "torpedo_growth": 4491,
    "luck": 0,
    "speed_growth": 0,
    "dodge": 15,
    "luck_growth": 0,
    "star": 6,
    "base": 167,
    "torpedo": 54,
    "air": 0,
    "battle_unit_type": 50,
    "cannon": 6,
    "hit_growth": 210,
    "id": 10031014,
    "speed": 32,
    "cannon_growth": 468,
    "reload": 150,
    "antiaircraft": 20,
    "durability_growth": 25100,
    "armor_growth": 0,
    "hit": 14,
    "rarity": 5,
    "antisub_growth": 0,
    "dodge_growth": 222,
    "pilot_ai_template_id": 10001
  },
  "10031007": {
    "durability": 440,
    "equipment_list": [
      100205,
      100506,
      100406
    ],
    "appear_fx": [
      "appearsmall"
    ],
    "air_growth": 0,
    "reload_growth": 0,
    "smoke": [
      [
        70,
        [
          [
            "smoke",
            [
              -1.35,
              1.17,
              0.51
            ]
          ]
        ]
      ],
      [
        50,
        [
          [
            "smoke",
            [
              1.39,
              1.41,
              0.54
            ]
          ]
        ]
      ],
      [
        40,
        [
          [
            "smoke",
            [
              0.02,
              1.82,
              0.76
            ]
          ]
        ]
      ]
    ],
    "antisub": 0,
    "antiaircraft_growth": 990,
    "torpedo_growth": 954,
    "luck": 0,
    "speed_growth": 0,
    "dodge": 0,
    "armor": 0,
    "star": 3,
    "base": 113,
    "torpedo": 12,
    "air": 0,
    "battle_unit_type": 30,
    "cannon": 12,
    "hit_growth": 120,
    "id": 10031007,
    "speed": 15,
    "cannon_growth": 990,
    "reload": 150,
    "antiaircraft": 12,
    "durability_growth": 24500,
    "armor_growth": 0,
    "hit": 8,
    "luck_growth": 0,
    "rarity": 2,
    "antisub_growth": 0,
    "dodge_growth": 0
  },
  "10031015": {
    "durability": 930,
    "armor": 0,
    "appear_fx": [
      "appearQ"
    ],
    "air_growth": 0,
    "reload_growth": 0,
    "equipment_list": [
      400403,
      400501,
      400404
    ],
    "antisub": 0,
    "antiaircraft_growth": 3744,
    "torpedo_growth": 3366,
    "luck": 0,
    "speed_growth": 0,
    "dodge": 11,
    "luck_growth": 0,
    "star": 3,
    "base": 188,
    "torpedo": 41,
    "air": 0,
    "battle_unit_type": 55,
    "cannon": 11,
    "hit_growth": 210,
    "id": 10031015,
    "speed": 25,
    "cannon_growth": 936,
    "reload": 150,
    "antiaircraft": 35,
    "durability_growth": 29500,
    "armor_growth": 0,
    "hit": 14,
    "rarity": 2,
    "antisub_growth": 0,
    "dodge_growth": 162,
    "pilot_ai_template_id": 10001
  },
  "10031008": {
    "durability": 420,
    "appear_fx": [
      "appearsmall"
    ],
    "air_growth": 0,
    "reload_growth": 0,
    "equipment_list": [
      100205,
      100506,
      100406
    ],
    "antisub": 0,
    "antiaircraft_growth": 990,
    "torpedo_growth": 954,
    "luck": 0,
    "speed_growth": 0,
    "dodge": 0,
    "armor": 0,
    "star": 3,
    "base": 112,
    "torpedo": 12,
    "air": 0,
    "battle_unit_type": 30,
    "cannon": 12,
    "hit_growth": 120,
    "id": 10031008,
    "speed": 15,
    "cannon_growth": 990,
    "reload": 150,
    "antiaircraft": 12,
    "durability_growth": 24000,
    "armor_growth": 0,
    "hit": 8,
    "luck_growth": 0,
    "rarity": 2,
    "antisub_growth": 0,
    "dodge_growth": 0
  },
  "10031016": {
    "durability": 900,
    "air_growth": 0,
    "reload_growth": 0,
    "equipment_list": [
      400403,
      400501,
      400404
    ],
    "antisub": 0,
    "antiaircraft_growth": 3744,
    "torpedo_growth": 3366,
    "luck": 0,
    "speed_growth": 0,
    "dodge": 11,
    "armor": 0,
    "star": 3,
    "base": 185,
    "torpedo": 41,
    "air": 0,
    "battle_unit_type": 55,
    "cannon": 11,
    "hit_growth": 210,
    "id": 10031016,
    "speed": 25,
    "cannon_growth": 936,
    "reload": 150,
    "antiaircraft": 35,
    "durability_growth": 28900,
    "armor_growth": 0,
    "hit": 14,
    "luck_growth": 0,
    "rarity": 2,
    "antisub_growth": 0,
    "dodge_growth": 162
  },
  "10031009": {
    "durability": 750,
    "appear_fx": [
      "appearbig"
    ],
    "air_growth": 1476,
    "reload_growth": 0,
    "equipment_list": [
      100201,
      311044,
      311045,
      311046
    ],
    "antisub": 0,
    "antiaircraft_growth": 1521,
    "torpedo_growth": 0,
    "luck": 0,
    "speed_growth": 0,
    "dodge": 0,
    "armor": 0,
    "star": 6,
    "base": 121,
    "torpedo": 0,
    "air": 18,
    "battle_unit_type": 60,
    "cannon": 0,
    "hit_growth": 120,
    "id": 10031009,
    "speed": 15,
    "cannon_growth": 0,
    "reload": 150,
    "antiaircraft": 18,
    "durability_growth": 38000,
    "armor_growth": 0,
    "hit": 8,
    "luck_growth": 0,
    "rarity": 5,
    "antisub_growth": 0,
    "dodge_growth": 0
  },
  "10031017": {
    "durability": 930,
    "armor": 0,
    "air_growth": 0,
    "reload_growth": 0,
    "equipment_list": [
      400403,
      400501,
      400404
    ],
    "antisub": 0,
    "antiaircraft_growth": 3744,
    "torpedo_growth": 3366,
    "luck": 0,
    "speed_growth": 0,
    "dodge": 11,
    "luck_growth": 0,
    "star": 3,
    "base": 186,
    "torpedo": 41,
    "air": 0,
    "battle_unit_type": 55,
    "cannon": 11,
    "hit_growth": 210,
    "id": 10031017,
    "speed": 25,
    "cannon_growth": 936,
    "reload": 150,
    "antiaircraft": 35,
    "durability_growth": 29500,
    "armor_growth": 0,
    "hit": 14,
    "rarity": 2,
    "antisub_growth": 0,
    "dodge_growth": 162,
    "pilot_ai_template_id": 10001
  },
  "10031010": {
    "durability": 750,
    "air_growth": 0,
    "reload_growth": 0,
    "equipment_list": [
      100222,
      100432
    ],
    "antisub": 0,
    "antiaircraft_growth": 1638,
    "torpedo_growth": 4491,
    "luck": 0,
    "speed_growth": 0,
    "dodge": 15,
    "armor": 0,
    "star": 4,
    "base": 155,
    "torpedo": 54,
    "air": 0,
    "battle_unit_type": 50,
    "cannon": 6,
    "hit_growth": 210,
    "id": 10031010,
    "speed": 32,
    "cannon_growth": 468,
    "reload": 150,
    "antiaircraft": 20,
    "durability_growth": 24100,
    "armor_growth": 0,
    "hit": 14,
    "luck_growth": 0,
    "rarity": 3,
    "antisub_growth": 0,
    "dodge_growth": 222
  },
  "10031018": {
    "durability": 1020,
    "armor": 0,
    "air_growth": 0,
    "reload_growth": 0,
    "equipment_list": [
      100202,
      100512,
      100412,
      400502
    ],
    "antisub": 0,
    "antiaircraft_growth": 2340,
    "torpedo_growth": 2250,
    "luck": 0,
    "speed_growth": 0,
    "dodge": 6,
    "luck_growth": 0,
    "star": 4,
    "base": 201,
    "torpedo": 27,
    "air": 0,
    "battle_unit_type": 60,
    "cannon": 20,
    "hit_growth": 210,
    "id": 10031018,
    "speed": 16,
    "cannon_growth": 1638,
    "reload": 150,
    "antiaircraft": 28,
    "durability_growth": 41500,
    "armor_growth": 0,
    "hit": 14,
    "rarity": 3,
    "antisub_growth": 0,
    "dodge_growth": 84,
    "pilot_ai_template_id": 10001
  },
  "10031011": {
    "durability": 750,
    "air_growth": 0,
    "reload_growth": 0,
    "equipment_list": [
      100222,
      100432
    ],
    "antisub": 0,
    "antiaircraft_growth": 1638,
    "torpedo_growth": 4491,
    "luck": 0,
    "speed_growth": 0,
    "dodge": 15,
    "armor": 0,
    "star": 4,
    "base": 156,
    "torpedo": 54,
    "air": 0,
    "battle_unit_type": 50,
    "cannon": 6,
    "hit_growth": 210,
    "id": 10031011,
    "speed": 32,
    "cannon_growth": 468,
    "reload": 150,
    "antiaircraft": 20,
    "durability_growth": 24100,
    "armor_growth": 0,
    "hit": 14,
    "luck_growth": 0,
    "rarity": 3,
    "antisub_growth": 0,
    "dodge_growth": 222
  },
  "10031012": {
    "durability": 750,
    "armor": 0,
    "air_growth": 0,
    "reload_growth": 0,
    "equipment_list": [
      100222,
      100432
    ],
    "antisub": 0,
    "antiaircraft_growth": 1638,
    "torpedo_growth": 4491,
    "luck": 0,
    "speed_growth": 0,
    "dodge": 15,
    "luck_growth": 0,
    "star": 4,
    "base": 161,
    "torpedo": 54,
    "air": 0,
    "battle_unit_type": 50,
    "cannon": 6,
    "hit_growth": 210,
    "id": 10031012,
    "speed": 32,
    "cannon_growth": 468,
    "reload": 150,
    "antiaircraft": 20,
    "durability_growth": 24100,
    "armor_growth": 0,
    "hit": 14,
    "rarity": 3,
    "antisub_growth": 0,
    "dodge_growth": 222,
    "pilot_ai_template_id": 10001
  },
  "10031013": {
    "durability": 770,
    "armor": 0,
    "appear_fx": [
      "appearQ"
    ],
    "air_growth": 0,
    "reload_growth": 0,
    "equipment_list": [
      400055,
      100432
    ],
    "antisub": 0,
    "antiaircraft_growth": 1638,
    "torpedo_growth": 4491,
    "luck": 0,
    "speed_growth": 0,
    "dodge": 15,
    "luck_growth": 0,
    "star": 4,
    "base": 160,
    "torpedo": 54,
    "air": 0,
    "battle_unit_type": 50,
    "cannon": 6,
    "hit_growth": 210,
    "id": 10031013,
    "speed": 32,
    "cannon_growth": 468,
    "reload": 150,
    "antiaircraft": 20,
    "durability_growth": 25100,
    "armor_growth": 0,
    "hit": 14,
    "rarity": 3,
    "antisub_growth": 0,
    "dodge_growth": 222,
    "pilot_ai_template_id": 10001
  }
}